Mensajes/__init__.py
Mensajes/Bienvenidas/Saludos.py
Mensajes/Bienvenidas/__init__.py
Mensajes/Despedidas/Adios.py
Mensajes/Despedidas/__init__.py
tests/__init__.py
tests/test_Bienvenidas.py
Mensajes_Armando_Rosas_Balderas-6.0.dist-info/LICENSE
Mensajes_Armando_Rosas_Balderas-6.0.dist-info/METADATA
Mensajes_Armando_Rosas_Balderas-6.0.dist-info/WHEEL
Mensajes_Armando_Rosas_Balderas-6.0.dist-info/top_level.txt
Mensajes_Armando_Rosas_Balderas-6.0.dist-info/RECORD
